{
"qucosa":"<p>1. Adam, M. et al.: Literaturverwaltungsprogramme im Überblick, <a href=\"http://nbn-resolving.de/urn:nbn:de:bsz:14-qucosa2-77350\" class=\"uri\">http://nbn-resolving.de/urn:nbn:de:bsz:14-qucosa2-77350</a>, (2016).</p>",
"tum-comparison":"<p>2. Böhner, D. et al.: Literaturverwaltungsprogramme im Vergleich, <a href=\"https://mediatum.ub.tum.de/1316333\" class=\"uri\">https://mediatum.ub.tum.de/1316333</a>, (2016).</p>",
"aigaion":"<p>3. Aigaion: Web based bibliography management system, <a href=\"https://sourceforge.net/projects/aigaion/\" class=\"uri\">https://sourceforge.net/projects/aigaion/</a>.</p>",
"bibsonomy-documents":"<p>4. BibSonomy – Attach a private document to publications, <a href=\"https://www.bibsonomy.org/help_en/AttachDocuments\" class=\"uri\">https://www.bibsonomy.org/help_en/AttachDocuments</a>.</p>",
"bibsonomy-export":"<p>5. BibSonomy – Export, <a href=\"https://www.bibsonomy.org/export\" class=\"uri\">https://www.bibsonomy.org/export</a>.</p>",
"refgrab-it":"<p>6. Capturing Web Page Data With RefGrab-It, <a href=\"https://www.refworks.com/refworks/help/Using_RefGrab-It_to_Capture_Web_Page_Data.htm\" class=\"uri\">https://www.refworks.com/refworks/help/Using_RefGrab-It_to_Capture_Web_Page_Data.htm</a>.</p>",
"citeulike-gold":"<p>7. CiteULike Gold, <a href=\"http://www.citeulike.org/gold\" class=\"uri\">http://www.citeulike.org/gold</a>.</p>",
"citeulike":"<p>8. CiteULike – Frequently Asked Questions, <a href=\"http://www.citeulike.org/faq/faq.adp\" class=\"uri\">http://www.citeulike.org/faq/faq.adp</a>.</p>",
"docear-citation":"<p>9. Docear: Citation Styles, <a href=\"http://www.docear.org/software/add-ons/docear4word/citation-styles/\" class=\"uri\">http://www.docear.org/software/add-ons/docear4word/citation-styles/</a>.</p>",
"docear":"<p>10. Docear: Details &amp; Features, <a href=\"http://www.docear.org/software/details/\" class=\"uri\">http://www.docear.org/software/details/</a>.</p>",
"f1000-user-guide":"<p>11. F1000Workspace user guide, <a href=\"http://f1000.com/resources/Workspace_User_Manual.FINAL.pdf\" class=\"uri\">http://f1000.com/resources/Workspace_User_Manual.FINAL.pdf</a>.</p>",
"f1000-faq-references":"<p>12. F1000Workspace: Help guide – Working with references, <a href=\"http://f1000.com/work/faq/references-in-f1000\" class=\"uri\">http://f1000.com/work/faq/references-in-f1000</a>.</p>",
"bibsonomy":"<p>13. Getting started with BibSonomy, <a href=\"https://www.bibsonomy.org/gettingStarted?lang=en\" class=\"uri\">https://www.bibsonomy.org/gettingStarted?lang=en</a>.</p>",
"jabref-search-engines":"<p>14. JabRef: Fetching entries from the web, <a href=\"http://help.jabref.org/en/#fetching-entries-from-the-web\" class=\"uri\">http://help.jabref.org/en/#fetching-entries-from-the-web</a>.</p>",
"jabref-collaborative-work":"<p>15. JabRef: Shared SQL Database, <a href=\"http://help.jabref.org/en/SQLDatabase\" class=\"uri\">http://help.jabref.org/en/SQLDatabase</a>.</p>",
"jabref-share":"<p>16. JabRef: Sharing a Bib(La)TeX Database, <a href=\"http://help.jabref.org/en/SharedBibFile\" class=\"uri\">http://help.jabref.org/en/SharedBibFile</a>.</p>",
"jabref-special-fields":"<p>17. JabRef: Special Fields, <a href=\"http://help.jabref.org/en/SpecialFields\" class=\"uri\">http://help.jabref.org/en/SpecialFields</a>.</p>",
"puma-open-source":"<p>18. PUMA goes Open Source, <a href=\"https://www.academic-puma.de/2014/12/12/puma-goes-open-source/\" class=\"uri\">https://www.academic-puma.de/2014/12/12/puma-goes-open-source/</a>, (2014).</p>",
"puma":"<p>19. PUMA: Kernfunktionen, <a href=\"https://www.academic-puma.de/puma/kernfunktionen/\" class=\"uri\">https://www.academic-puma.de/puma/kernfunktionen/</a>.</p>",
"bibsonomy-google-docs":"<p>20. Wiki: BibSonomy GoogleDocs Add-on – Home, <a href=\"https://bitbucket.org/fwhkoenig/bibsonomy-googledocs-add-on/wiki/Home\" class=\"uri\">https://bitbucket.org/fwhkoenig/bibsonomy-googledocs-add-on/wiki/Home</a>.</p>",
"bibsonomy-license":"<p>21. Wiki: BibSonomy – License, <a href=\"https://bitbucket.org/bibsonomy/bibsonomy/wiki/License\" class=\"uri\">https://bitbucket.org/bibsonomy/bibsonomy/wiki/License</a>.</p>",
"puma-license":"<p>22. Wiki: PUMA – Home, <a href=\"https://bitbucket.org/bibsonomy/puma/wiki/Home\" class=\"uri\">https://bitbucket.org/bibsonomy/puma/wiki/Home</a>.</p>"
}